Metadata-Version: 2.1
Name: copyscape-api
Version: 0.2
Summary: Python client for Copyscape API
Home-page: https://github.com/selentium/copyscape-api-client
Author: Vladimir Kadalashvili
Author-email: Kadalashvili.Vladimir@gmail.com
License: MIT
Platform: UNKNOWN
Classifier: Programming Language :: Python :: 3
Classifier: License :: OSI Approved :: MIT License
Classifier: Operating System :: OS Independent
